{
    "version": "2.0-beta.10",
    "description": "The ultimate automation scripting language for Windows.",
    "homepage": "https://www.autohotkey.com/",
    "license": "GPL-2.0-or-later",
    "architecture": {
        "64bit": {
            "url": "https://www.autohotkey.com/download/2.0/AutoHotkey_2.0-beta.10.zip",
            "hash": "98d4f37e7d68de87519ad388b4bdada6e2bc3100ca4a02d5513f52776ca0383e",
            "bin": [
                [
                    "autohotkeyu64.exe",
                    "ahk"
                ]
            ]
        },
        "32bit": {
            "url": "https://www.autohotkey.com/download/2.0/AutoHotkey_2.0-beta.10.zip",
            "hash": "98d4f37e7d68de87519ad388b4bdada6e2bc3100ca4a02d5513f52776ca0383e",
            "bin": [
                [
                    "autohotkeyu32.exe",
                    "ahk"
                ]
            ]
        }
    },
    "checkver": {
        "url": "https://www.autohotkey.com/download/2.0/?C=M;O=D",
        "regex": "AutoHotkey_([\\w-.+]+).zip"
    },
    "autoupdate": {
        "architecture": {
            "64bit": {
                "url": "https://www.autohotkey.com/download/2.0/AutoHotkey_$version.zip",
                "hash": {
                    "url": "https://www.autohotkey.com/download/2.0/AutoHotkey_$version.zip.sha256"
                }
            },
            "32bit": {
                "url": "https://www.autohotkey.com/download/2.0/AutoHotkey_$version.zip",
                "hash": {
                    "url": "https://www.autohotkey.com/download/2.0/AutoHotkey_$version.zip.sha256"
                }
            }
        }
    }
}
