{
    "version": "5.14.1",
    "description": "A prompt theme engine for any shell",
    "homepage": "https://ohmyposh.dev",
    "license": {
        "identifier": "GPL-3.0-only",
        "url": "https://github.com/JanDeDobbeleer/oh-my-posh/blob/main/COPYING"
    },
    "changelog": "https://github.com/JanDeDobbeleer/oh-my-posh/releases/tag/v5.14.1",
    "architecture": {
        "64bit": {
            "url": "https://github.com/JanDeDobbeleer/oh-my-posh/releases/download/v5.14.1/posh-windows-wsl-amd64.7z",
            "hash": "bc0bb6992ba5c3c09d3df623a2143a80d0dade156be99fe23fe40cc48ab797df"
        }
    },
    "bin": [
        "bin\\oh-my-posh.exe",
        "bin\\oh-my-posh-wsl"
    ],
    "checkver": {
        "github": "https://github.com/JanDeDobbeleer/oh-my-posh"
    },
    "autoupdate": {
        "changelog": "https://github.com/JanDeDobbeleer/oh-my-posh/releases/tag/v$version",
        "architecture": {
            "64bit": {
                "url": "https://github.com/JanDeDobbeleer/oh-my-posh/releases/download/v$version/posh-windows-wsl-amd64.7z"
            }
        },
        "hash": {
            "url": "$url.sha256"
        }
    }
}
